philz_pg_backup/__init__.py
philz_pg_backup/main.py
philz_pg_backup-0.1.1.dist-info/LICENSE.txt
philz_pg_backup-0.1.1.dist-info/LICENSES/MIT.txt
philz_pg_backup-0.1.1.dist-info/METADATA
philz_pg_backup-0.1.1.dist-info/WHEEL
philz_pg_backup-0.1.1.dist-info/entry_points.txt
philz_pg_backup-0.1.1.dist-info/RECORD
